musthe/__init__.py
musthe/musthe.py
musthe-1.0.0.dist-info/METADATA
musthe-1.0.0.dist-info/RECORD
musthe-1.0.0.dist-info/WHEEL
musthe-1.0.0.dist-info/top_level.txt
