Metadata-Version: 2.1
Name: musthe
Version: 1.0.0
Summary: Music theory implemented in Python. Notes, intervals, scales and chords.
Home-page: https://github.com/gciruelos/musthe
Author: Gonzalo Ciruelos
Author-email: gonzalo.ciruelos@gmail.com 
License: MIT
Platform: UNKNOWN
Classifier: License :: OSI Approved :: MIT License
Classifier: Programming Language :: Python
Classifier: Programming Language :: Python :: 3
Classifier: Programming Language :: Python :: Implementation :: CPython
Requires-Python: >=3.4
